recordclass/__init__.py
recordclass/_dataobject.c
recordclass/_dataobject.cp310-win_amd64.pyd
recordclass/_dataobject.h
recordclass/_linkedlist.c
recordclass/_linkedlist.cp310-win_amd64.pyd
recordclass/_linkedlist.h
recordclass/_linkedlist.pyx
recordclass/_litelist.c
recordclass/_litelist.cp310-win_amd64.pyd
recordclass/_litelist.h
recordclass/_litetuple.c
recordclass/_litetuple.cp310-win_amd64.pyd
recordclass/about.py
recordclass/adapter.py
recordclass/arrayclass.py
recordclass/dataclass.py
recordclass/datatype.py
recordclass/dictclass.py
recordclass/recordclass.py
recordclass/utils.py
recordclass/test/__init__.py
recordclass/test/test_arrayclass.py
recordclass/test/test_dataobject.py
recordclass/test/test_litelist.py
recordclass/test/test_litetuple.py
recordclass/test/test_recordclass.py
recordclass/test/test_sqlite.py
recordclass/test/match/__init__.py
recordclass/test/match/test_dataobject_match.py
recordclass/test/typing/__init__.py
recordclass/test/typing/test_dataobject.py
recordclass/test/typing/test_datastruct.py
recordclass/test/typing/test_recordclass.py
recordclass/tools/__init__.py
recordclass/tools/csv_dataobject.py
recordclass/tools/perfcounts.py
recordclass/tools/sqlite.py
recordclass/typing/__init__.py
recordclass-0.23.1.dist-info/licenses/LICENSE.txt
recordclass-0.23.1.dist-info/METADATA
recordclass-0.23.1.dist-info/WHEEL
recordclass-0.23.1.dist-info/top_level.txt
recordclass-0.23.1.dist-info/RECORD
