Metadata-Version: 2.1
Name: recordclass
Version: 0.23.1
Summary: Mutable variant of namedtuple -- recordclass, which support assignments, compact dataclasses and other memory saving variants.
Home-page: https://github.com/intellimath/recordclass
Download-URL: https://pypi.org/project/recordclass/#files
Author: Zaur Shibzukhov
Author-email: Zaur Shibzukhov <szport@gmail.com>
License: The MIT License (MIT)
Keywords: dataclass,namedtuple,recordclass,dataobject
Platform: Linux
Platform: Mac OS X
Platform: Windows
Classifier: Development Status :: 4 - Beta
Classifier: Intended Audience :: Science/Research
Classifier: Intended Audience :: Developers
Classifier: License :: OSI Approved :: BSD License
Classifier: Operating System :: OS Independent
Classifier: Programming Language :: Cython
Classifier: Programming Language :: Python :: 3
Classifier: Programming Language :: Python :: 3.8
Classifier: Programming Language :: Python :: 3.9
Classifier: Programming Language :: Python :: 3.10
Classifier: Programming Language :: Python :: 3.11
Classifier: Programming Language :: Python :: 3.12
Classifier: Programming Language :: Python :: 3.13
Classifier: Topic :: Software Development :: Libraries :: Python Modules
Requires-Python: >=3.8
License-File: LICENSE.txt
